[{"data":1,"prerenderedAt":126},["Reactive",2],{"BZMrOYVjtt":3},{"OverrideNameTextID":4,"NamePrefixID":5,"OverridePartnerSkillTextID":5,"IsPal":6,"Tribe":7,"BPClass":8,"ZukanIndex":9,"ZukanIndexSuffix":10,"Size":11,"Rarity":12,"ElementType1":13,"ElementType2":14,"GenusCategory":15,"Organization":16,"weapon":17,"WeaponEquip":18,"HP":19,"MeleeAttack":20,"ShotAttack":21,"Defense":22,"Support":23,"CraftSpeed":19,"EnemyReceiveDamageRate":24,"CaptureRateCorrect":24,"ExpRatio":24,"Price":25,"AIResponse":26,"AISightResponse":5,"SlowWalkSpeed":20,"WalkSpeed":27,"RunSpeed":28,"RideSprintSpeed":29,"TransportSpeed":30,"IsBoss":18,"IsTowerBoss":18,"BattleBGM":31,"IgnoreLeanBack":18,"IgnoreBlowAway":18,"MaxFullStomach":32,"FullStomachDecreaseRate":24,"FoodAmount":12,"ViewingDistance":33,"ViewingAngle":34,"HearingRate":24,"NooseTrap":18,"Nocturnal":18,"BiologicalGrade":35,"Predator":18,"Edible":6,"Stamina":19,"MaleProbability":23,"CombiRank":36,"WorkSuitability_EmitFlame":37,"WorkSuitability_Watering":38,"WorkSuitability_Seeding":38,"WorkSuitability_GenerateElectricity":38,"WorkSuitability_Handcraft":38,"WorkSuitability_Collection":38,"WorkSuitability_Deforest":38,"WorkSuitability_Mining":39,"WorkSuitability_OilExtraction":38,"WorkSuitability_ProductMedicine":38,"WorkSuitability_Cool":38,"WorkSuitability_Transport":38,"WorkSuitability_MonsterFarm":38,"PassiveSkill1":40,"PassiveSkill2":5,"PassiveSkill3":5,"PassiveSkill4":5,"PartnerSkillName":41,"PartnerSkillDesc":42,"Combinations":43,"PrefixName":44,"Drops":45,"ActiveSkills":54,"PassiveSkills":116,"Description":125},"Blazamut","None",true,"EPalTribeID::KingBahamut","KingBahamut",96,"","EPalSizeType::XL",9,"EPalElementType::Fire","EPalElementType::None","EPalGenusCategoryType::FourLegged","EPalOrganizationType::None","EPalWeaponType::None",false,100,150,125,120,50,1,10520,"Warlike",400,700,900,500,"EPalBattleBGMType::Strong",600,25,90,5,10,3,0,4,"ElementBoost_Fire_2_PAL","Magma Kaiser","Can be ridden.\r\nEnhances \u003CuiCommon id=|COMMON_ELEMENT_NAME_Fire|/> attacks while mounted.",[],"Cursed Tyrant",[46,50],{"max":36,"min":36,"rate":19,"name":47,"descr":48,"icon":49},"Coal","\u003CitemName id=|Coal|/> often found in caves and other places.\r\nRequired to create high quality metal.","T_itemicon_Material_Coal",{"max":36,"min":36,"rate":19,"name":51,"descr":52,"icon":53},"Flame Organ","Material obtainable from \u003CuiCommon id=|COMMON_ELEMENT_NAME_Fire|/> Pals.\r\nCan be used to make \u003CitemName id=|Arrow_Fire|/> and more.","T_itemicon_Material_FireOrgan",[55,67,77,87,96,104,111],{"WazaType":56,"Element":57,"IgnoreRandomInherit":18,"Category":58,"Power":59,"IsLeanBack":18,"CameraShake":60,"MinRange":32,"MaxRange":61,"CoolTime":39,"ForceRagdollSize":62,"EffectType1":63,"EffectValue1":38,"EffectValueEx1":38,"EffectType2":63,"EffectValue2":38,"EffectValueEx2":38,"SpecialAttackRateInfos":64,"bIsWeaponDamage":18,"DisabledData":18,"Level":24,"WazaName":65,"WazaDesc":66},"EPalWazaID::PowerShot","EPalElementType::Normal","EPalWazaCategory::Shot",35,"EPalPlayerDamageCameraShakeCategory::Waza_S",3000,"EPalSizeType::None","EPalAdditionalEffectType::None",[],"Power Shot","Charges energy\r\ninto a focused blast.",{"WazaType":68,"Element":13,"IgnoreRandomInherit":18,"Category":58,"Power":69,"IsLeanBack":18,"CameraShake":60,"MinRange":30,"MaxRange":70,"CoolTime":71,"ForceRagdollSize":62,"EffectType1":72,"EffectValue1":23,"EffectValueEx1":38,"EffectType2":63,"EffectValue2":38,"EffectValueEx2":38,"SpecialAttackRateInfos":73,"bIsWeaponDamage":18,"DisabledData":18,"Level":74,"WazaName":75,"WazaDesc":76},"EPalWazaID::FireBlast",30,5000,2,"EPalAdditionalEffectType::Burn",[],7,"Ignis Blast","Hurls a ball of fire\r\nstraight at an enemy.",{"WazaType":78,"Element":79,"IgnoreRandomInherit":18,"Category":58,"Power":80,"IsLeanBack":18,"CameraShake":60,"MinRange":30,"MaxRange":81,"CoolTime":36,"ForceRagdollSize":62,"EffectType1":82,"EffectValue1":19,"EffectValueEx1":38,"EffectType2":63,"EffectValue2":38,"EffectValueEx2":38,"SpecialAttackRateInfos":83,"bIsWeaponDamage":18,"DisabledData":18,"Level":84,"WazaName":85,"WazaDesc":86},"EPalWazaID::StoneShotgun","EPalElementType::Earth",55,4000,"EPalAdditionalEffectType::Muddy",[],15,"Stone Blast","Fires a barrage of stones forward.",{"WazaType":88,"Element":13,"IgnoreRandomInherit":18,"Category":58,"Power":89,"IsLeanBack":18,"CameraShake":90,"MinRange":30,"MaxRange":91,"CoolTime":84,"ForceRagdollSize":62,"EffectType1":72,"EffectValue1":19,"EffectValueEx1":38,"EffectType2":63,"EffectValue2":38,"EffectValueEx2":38,"SpecialAttackRateInfos":92,"bIsWeaponDamage":18,"DisabledData":18,"Level":93,"WazaName":94,"WazaDesc":95},"EPalWazaID::Flamethrower",70,"EPalPlayerDamageCameraShakeCategory::Waza_M",1500,[],22,"Ignis Breath","Shoots flames at an enemy,\r\ndealing continuous damage.",{"WazaType":97,"Element":13,"IgnoreRandomInherit":18,"Category":58,"Power":22,"IsLeanBack":18,"CameraShake":98,"MinRange":19,"MaxRange":99,"CoolTime":100,"ForceRagdollSize":62,"EffectType1":72,"EffectValue1":19,"EffectValueEx1":38,"EffectType2":63,"EffectValue2":38,"EffectValueEx2":38,"SpecialAttackRateInfos":101,"bIsWeaponDamage":18,"DisabledData":18,"Level":69,"WazaName":102,"WazaDesc":103},"EPalWazaID::Inferno","EPalPlayerDamageCameraShakeCategory::Waza_L",1000,40,[],"Ignis Rage","Energizes the surrounding ground,\r\ncausing it to explode after a set amount of time.",{"WazaType":105,"Element":13,"IgnoreRandomInherit":18,"Category":58,"Power":20,"IsLeanBack":18,"CameraShake":98,"MinRange":30,"MaxRange":106,"CoolTime":80,"ForceRagdollSize":107,"EffectType1":72,"EffectValue1":19,"EffectValueEx1":38,"EffectType2":63,"EffectValue2":38,"EffectValueEx2":38,"SpecialAttackRateInfos":108,"bIsWeaponDamage":18,"DisabledData":18,"Level":100,"WazaName":109,"WazaDesc":110},"EPalWazaID::FireBall",9999,"EPalSizeType::S",[],"Fire Ball","Creates a giant ball of flame and hurls it at an enemy.\r\nThe ball explodes over a wide area upon impact.",{"WazaType":112,"Element":79,"IgnoreRandomInherit":18,"Category":58,"Power":20,"IsLeanBack":18,"CameraShake":98,"MinRange":19,"MaxRange":106,"CoolTime":80,"ForceRagdollSize":62,"EffectType1":82,"EffectValue1":19,"EffectValueEx1":38,"EffectType2":63,"EffectValue2":38,"EffectValueEx2":38,"SpecialAttackRateInfos":113,"bIsWeaponDamage":18,"DisabledData":18,"Level":23,"WazaName":114,"WazaDesc":115},"EPalWazaID::RockLance",[],"Rock Lance","Generates a sharp rock spear\r\nunder an enemy.",[117],{"Rank":37,"OverrideDescMsgID":118,"EffectType1":119,"EffectValue1":120,"TargetType1":121,"EffectType2":122,"EffectValue2":38,"TargetType2":121,"EffectType3":122,"EffectValue3":38,"TargetType3":121,"InvokeActiveOtomo":18,"InvokeWorker":18,"InvokeRiding":18,"InvokeReserve":18,"InvokeInOtomo":18,"InvokeAlways":6,"AddPal":18,"AddRarePal":18,"AddShotWeapon":18,"AddMeleeWeapon":18,"AddArmor":18,"AddAccessory":18,"OverrideNameTextID":5,"OverrideSummaryTextId":5,"Description":123,"Name":124},"PASSIVE_ElementBoost_Fire_1_PAL","EPalPassiveSkillEffectType::ElementBoost_Fire",20,"EPalPassiveSkillEffectTargetType::ToSelf","EPalPassiveSkillEffectType::no","{EffectValue1}% increase to Fire attack damage.","Flame Emperor","Legends say it was born during a volcanic eruption.\r\nA strange group even claims that this continent is laid upon\r\nthe back of a giant \u003CcharacterName id=|KingBahamut|/>.",1706864122867]