{
  "name": "Sparkit",
  "title": "Livewire Tabby",
  "image": "/images/full_palicon/T_ElecCat_icon_normal.png",
  "rarity": {
    "name": "Common",
    "level": "1",
    "class": "common"
  },
  "elements": [
    {
      "name": "Electricity",
      "image": "/images/icons/T_Icon_element_s_03.png",
      "className": "elm6"
    }
  ],
  "description": "During the dry season,\nthis Pal is always on the verge of blowing a fuse.\nSparks can fly with even the slightest provocation,\neven amongst allies.",
  "drops": [
    {
      "image": "/images/items/T_itemicon_Material_ElectricOrgan.png",
      "name": "Electric Organ",
      "amount": "1 - 2",
      "rate": "100%"
    }
  ],
  "stats": [
    {
      "name": "HP",
      "value": "60"
    },
    {
      "name": "Defense",
      "value": "70"
    },
    {
      "name": "Crafting Speed",
      "value": "100"
    },
    {
      "name": "Melee Attack",
      "value": "60"
    },
    {
      "name": "Shot Attack",
      "value": "75"
    },
    {
      "name": "Price",
      "value": "1030"
    },
    {
      "name": "Stamina",
      "value": "100"
    },
    {
      "name": "Support",
      "value": "80"
    },
    {
      "name": "Running Speed",
      "value": "350"
    },
    {
      "name": "Ride Sprint Speed",
      "value": "500"
    },
    {
      "name": "Slow Walk Speed",
      "value": "40"
    }
  ],
  "uniqueCombinations": [
    {
      "male": {
        "name": "Relaxaurus",
        "image": "/images/palicon/T_LazyDragon_icon_normal.png"
      },
      "female": {
        "name": "Sparkit",
        "image": "/images/palicon/T_ElecCat_icon_normal.png"
      },
      "result": {
        "name": "Relaxaurus Lux",
        "image": "/images/palicon/T_LazyDragon_Electric_icon_normal.png"
      }
    }
  ],
  "workSuitability": [
    {
      "name": "Gathering",
      "isActive": false,
      "level": null,
      "image": "/images/icons/T_icon_palwork_05.png"
    },
    {
      "name": "Cooling",
      "isActive": false,
      "level": null,
      "image": "/images/icons/T_icon_palwork_10.png"
    },
    {
      "name": "Deforesting",
      "isActive": false,
      "level": null,
      "image": "/images/icons/T_icon_palwork_06.png"
    },
    {
      "name": "Kindling",
      "isActive": false,
      "level": null,
      "image": "/images/icons/T_icon_palwork_00.png"
    },
    {
      "name": "Generating Electricity",
      "isActive": true,
      "level": "1",
      "image": "/images/icons/T_icon_palwork_03.png"
    },
    {
      "name": "Handiwork",
      "isActive": true,
      "level": "1",
      "image": "/images/icons/T_icon_palwork_04.png"
    },
    {
      "name": "Mining",
      "isActive": false,
      "level": null,
      "image": "/images/icons/T_icon_palwork_07.png"
    },
    {
      "name": "Farming",
      "isActive": false,
      "level": null,
      "image": "/images/icons/T_icon_palwork_12.png"
    },
    {
      "name": "Oil Extracting",
      "isActive": false,
      "level": null,
      "image": "/images/icons/T_icon_palwork_09.png"
    },
    {
      "name": "Medicine Production",
      "isActive": false,
      "level": null,
      "image": "/images/icons/T_icon_palwork_08.png"
    },
    {
      "name": "Planting",
      "isActive": false,
      "level": null,
      "image": "/images/icons/T_icon_palwork_02.png"
    },
    {
      "name": "Transporting",
      "isActive": true,
      "level": "1",
      "image": "/images/icons/T_icon_palwork_11.png"
    },
    {
      "name": "Watering",
      "isActive": false,
      "level": null,
      "image": "/images/icons/T_icon_palwork_01.png"
    }
  ],
  "partnerSkill": {
    "name": "Static Electricity",
    "description": "While in team, increases attack power of COMMON_ELEMENT_NAME_Electricity Pals."
  },
  "activeSkills": [
    {
      "name": "Spark Blast",
      "level": "- Lv 1",
      "image": "/images/icons/T_Icon_element_s_03.png",
      "power": "30",
      "coolDown": "2",
      "range": "500 - 5000",
      "description": "The user releases a lightning ball\nthat expands outward in a forward, circular pattern."
    },
    {
      "name": "Sand Blast",
      "level": "- Lv 7",
      "image": "/images/icons/T_Icon_element_s_07.png",
      "power": "40",
      "coolDown": "4",
      "range": "500 - 3000",
      "description": "Hurls sticky mud\nat an enemy."
    },
    {
      "name": "Shockwave",
      "level": "- Lv 15",
      "image": "/images/icons/T_Icon_element_s_03.png",
      "power": "40",
      "coolDown": "4",
      "range": "0 - 300",
      "description": "Quickly discharges electricity,\nshocking those around it."
    },
    {
      "name": "Electric Ball",
      "level": "- Lv 22",
      "image": "/images/icons/T_Icon_element_s_03.png",
      "power": "50",
      "coolDown": "9",
      "range": "500 - 2500",
      "description": "Fires an electric ball\nthat slowly pursues an enemy."
    },
    {
      "name": "Tri-Lightning",
      "level": "- Lv 30",
      "image": "/images/icons/T_Icon_element_s_03.png",
      "power": "90",
      "coolDown": "22",
      "range": "0 - 9999",
      "description": "Generates lightning that strikes\nan enemy three times from above."
    },
    {
      "name": "Lightning Streak",
      "level": "- Lv 40",
      "image": "/images/icons/T_Icon_element_s_03.png",
      "power": "75",
      "coolDown": "16",
      "range": "500 - 2000",
      "description": "Generates a lightning bolt\nthat moves forward in a line."
    },
    {
      "name": "Lightning Bolt",
      "level": "- Lv 50",
      "image": "/images/icons/T_Icon_element_s_03.png",
      "power": "150",
      "coolDown": "55",
      "range": "500 - 3000",
      "description": "Charges electric energy before\nblasting enemies with a powerful shock."
    }
  ],
  "uniqueName": "sparkit"
}